mindspace_protocol/__init__.py
mindspace_protocol-2.0.0.dist-info/AUTHORS
mindspace_protocol-2.0.0.dist-info/LICENSE
mindspace_protocol-2.0.0.dist-info/METADATA
mindspace_protocol-2.0.0.dist-info/WHEEL
mindspace_protocol-2.0.0.dist-info/pbr.json
mindspace_protocol-2.0.0.dist-info/top_level.txt
mindspace_protocol-2.0.0.dist-info/RECORD
