Metadata-Version: 2.1
Name: mindspace-protocol
Version: 2.0.0
Summary: The Mindspace protocol.
Home-page: https://github.com/chrisnorman7/
Author: Chris Norman
Author-email: chris.norman2@googlemail.com
License: MPL-2
Platform: UNKNOWN
Requires-Dist: attrs
